{
  "idea": {
    "topic": "Black Hole Event Horizon Scale",
    "topic_family": "scale_comparison",
    "hook": "How big is a black hole's 'mouth' compared to our entire Solar System?",
    "facts": [
      "Our Solar System, out to Neptune's orbit, spans roughly 9 billion kilometers (5.6 billion miles) across.",
      "The supermassive black hole in our Milky Way, Sagittarius A*, has an event horizon only about 44 million kilometers (27 million miles) wide.",
      "But the supermassive black hole in galaxy M87, M87*, has an event horizon spanning a mind-boggling 38 billion kilometers (24 billion miles) across!"
    ],
    "payoff": "M87*'s event horizon could swallow our entire Solar System (out to Neptune) over 4 times!",
    "title": "Black Hole's Mouth vs. Our Solar System! \ud83e\udd2f\ud83c\udf0c",
    "hashtags": [
      "#Astrophysics",
      "#BlackHole",
      "#SpaceFacts",
      "#ScaleComparison",
      "#Universe"
    ],
    "generated_at": "2026-04-26T16:32:54.224555",
    "status": "pending",
    "strategy_based": true
  },
  "script": {
    "total_duration": 20,
    "scenes": [
      {
        "scene_number": 1,
        "start_time": 0,
        "duration": 3,
        "text": "How big is a black hole's 'mouth' vs. our Solar System?",
        "text_position": "center",
        "text_size": "large",
        "visual": "A captivating animation of a stylized black hole event horizon swirling, then a simplified outline of our Solar System fading in beside it, showing a size comparison that's initially ambiguous.",
        "animation": "fade_in"
      },
      {
        "scene_number": 2,
        "start_time": 3,
        "duration": 4,
        "text": "Our Solar System (to Neptune): 9 BILLION km wide.",
        "text_position": "center",
        "text_size": "medium",
        "visual": "A detailed, stylized infographic of our Solar System (Sun, planets as dots, Kuiper belt outline) with an arrow showing its 9 billion km diameter. The numerical value animates in prominently.",
        "animation": "zoom_in"
      },
      {
        "scene_number": 3,
        "start_time": 7,
        "duration": 4,
        "text": "Milky Way's Sgr A*: 44 MILLION km wide.",
        "text_position": "center",
        "text_size": "medium",
        "visual": "The Solar System graphic from Scene 2 shrinks dramatically and moves to the left. A small, glowing black hole event horizon graphic (Sagittarius A*) appears to its right, with its 44 million km diameter highlighted, dwarfed by the previous scale.",
        "animation": "slide_left"
      },
      {
        "scene_number": 4,
        "start_time": 11,
        "duration": 4,
        "text": "Galaxy M87's M87*: 38 BILLION km wide!",
        "text_position": "center",
        "text_size": "medium",
        "visual": "The previous Sgr A* and shrunken Solar System graphics slide off screen. A colossal, menacing black hole event horizon graphic (M87*) slides in from the right, filling most of the screen, with its 38 billion km diameter clearly labeled.",
        "animation": "slide_right"
      },
      {
        "scene_number": 5,
        "start_time": 15,
        "duration": 5,
        "text": "M87* could SWALLOW our Solar System 4+ times!",
        "text_position": "center",
        "text_size": "large",
        "animation": "pulse",
        "visual": "The massive M87* event horizon remains central. The Solar System graphic from Scene 2 reappears, looking tiny in comparison, and is shown being completely enveloped by the M87* event horizon, repeating the 'swallowing' action multiple times to emphasize the scale."
      }
    ],
    "thumbnail_text": "BLACK HOLE SCALE!",
    "background_style": "space_dark"
  },
  "formatted_at": "2026-04-26T16:33:03.613082",
  "status": "uploaded",
  "rendered_at": "2026-04-26T16:33:58.503251",
  "video_path": "videos_output/black_hole_event_horizon_scale_20260426_163303.mp4",
  "uploaded_at": "2026-04-26T16:34:01.799830",
  "youtube": {
    "video_id": "PQeUq8d1dcg",
    "url": "https://youtube.com/shorts/PQeUq8d1dcg",
    "title": "Black Hole's Mouth vs. Our Solar System! \ud83e\udd2f\ud83c\udf0c",
    "uploaded_at": "2026-04-26T16:34:01.799716"
  }
}